bssl_build/__init__.py
bssl_build/libcrypto.so
bssl_build/libssl.so
bssl_build-0.0.1.dist-info/METADATA
bssl_build-0.0.1.dist-info/WHEEL
bssl_build-0.0.1.dist-info/top_level.txt
bssl_build-0.0.1.dist-info/RECORD
